contexter.py
contexter-0.1.4.dist-info/DESCRIPTION.rst
contexter-0.1.4.dist-info/METADATA
contexter-0.1.4.dist-info/RECORD
contexter-0.1.4.dist-info/WHEEL
contexter-0.1.4.dist-info/metadata.json
contexter-0.1.4.dist-info/top_level.txt
