Metadata-Version: 2.0
Name: contexter
Version: 0.1.4
Summary: 
